valenoq_utils/__init__.py
valenoq_utils/config.py
valenoq_utils/log.py
valenoq_utils/reply.py
valenoq_utils-0.2.dist-info/METADATA
valenoq_utils-0.2.dist-info/WHEEL
valenoq_utils-0.2.dist-info/top_level.txt
valenoq_utils-0.2.dist-info/RECORD
