Metadata-Version: 2.1
Name: valenoq-utils
Version: 0.2
Summary: valenoq.com utils
Home-page: http://github.com/samarkanov/valenoq_utils
Author: Dmitry Samarkanov
Author-email: samarkanov@gmail.com
License: MIT
Platform: UNKNOWN
